[{"name":"Cow"},
{"name":"Rabbit"},
{"name":"Ducks"},
{"name":"Shrimp"},
{"name":"Pig"},
{"name":"Goat"},
{"name":"Crab"},
{"name":"Deer"},
{"name":"Bee"},
{"name":"Sheep"},
{"name":"Fish"},
{"name":"Turkey"},
{"name":"Crow"},
{"name":"Peacock"},
{"name":"Dove"},
{"name":"Sparrow"},
{"name":"Goose"},
{"name":"Stork"},
{"name":"Pigeon"},
{"name":"Hawk"},
{"name":"Bald eagle"},
{"name":"Raven"},
{"name":"Parrot"},
{"name":"Flamingo"},
{"name":"Seagull"},
{"name":"Ostrich"},
{"name":"Swallow"},
{"name":"Black bird"},
{"name":"Robin"},
{"name":"Swan"},
{"name":"Owl"},
{"name":"Woodpecker"},
{"name":"Penguin"},
{"name":"Chicken"},
{"name":"Horse"},
{"name":"Turkey"},
{"name":"Farm Animal"}]










